eth_hentai/abi/BaseBoringBatchable.json
eth_hentai/abi/BentoBoxV1.json
eth_hentai/abi/BoringBatchable.json
eth_hentai/abi/BoringERC20.json
eth_hentai/abi/BoringFactory.json
eth_hentai/abi/BoringMath.json
eth_hentai/abi/BoringMath128.json
eth_hentai/abi/BoringMath32.json
eth_hentai/abi/BoringMath64.json
eth_hentai/abi/BoringOwnable.json
eth_hentai/abi/BoringOwnableData.json
eth_hentai/abi/CloneRewarderTime.json
eth_hentai/abi/CloneRewarderTimeDual.json
eth_hentai/abi/ComplexRewarder.json
eth_hentai/abi/ComplexRewarderTime.json
eth_hentai/abi/Domain.json
eth_hentai/abi/ERC20.json
eth_hentai/abi/ERC20Data.json
eth_hentai/abi/ERC20Mock.json
eth_hentai/abi/ERC20MockDecimals.json
eth_hentai/abi/IBatchFlashBorrower.json
eth_hentai/abi/IBentoBoxV1.json
eth_hentai/abi/IBentoBoxWithdraw.json
eth_hentai/abi/IERC20.json
eth_hentai/abi/IERC20Uniswap.json
eth_hentai/abi/IFlashBorrower.json
eth_hentai/abi/IKashiWithdrawFee.json
eth_hentai/abi/IMasterChef.json
eth_hentai/abi/IMasterChefV2.json
eth_hentai/abi/IMasterContract.json
eth_hentai/abi/IMigrator.json
eth_hentai/abi/IMigratorChef.json
eth_hentai/abi/IMiniChefV2.json
eth_hentai/abi/IOracle.json
eth_hentai/abi/IRewarder.json
eth_hentai/abi/IStrategy.json
eth_hentai/abi/ISwapper.json
eth_hentai/abi/IUniswapV2Callee.json
eth_hentai/abi/IUniswapV2ERC20.json
eth_hentai/abi/IUniswapV2Factory.json
eth_hentai/abi/IUniswapV2Pair.json
eth_hentai/abi/IUniswapV2Router01.json
eth_hentai/abi/IUniswapV2Router02.json
eth_hentai/abi/IWETH.json
eth_hentai/abi/KashiPairMediumRiskV1.json
eth_hentai/abi/MalformedERC20.json
eth_hentai/abi/MasterChef.json
eth_hentai/abi/MasterChefV2.json
eth_hentai/abi/MasterContractManager.json
eth_hentai/abi/Math.json
eth_hentai/abi/Migrator.json
eth_hentai/abi/MiniChefV2.json
eth_hentai/abi/Multicall2.json
eth_hentai/abi/Ownable.json
eth_hentai/abi/OwnableData.json
eth_hentai/abi/PeggedOracleV1.json
eth_hentai/abi/RebaseLibrary.json
eth_hentai/abi/RewarderBrokenMock.json
eth_hentai/abi/RewarderMock.json
eth_hentai-0.6.1.dist-info/WHEEL
eth_hentai-0.6.1.dist-info/METADATA
eth_hentai-0.6.1.dist-info/RECORD
